<GenericClientQuery>
<NetworkObjectData>
<NetworkParameter>APPLICATION</NetworkParameter>
<SelectColumnList>
<ClientColumn>networkServiceId</ClientColumn>
<ClientColumn>ipAddress</ClientColumn>
<ClientColumn>ifn</ClientColumn>
<ClientColumn>octets</ClientColumn>
<ClientColumn>targetTime</ClientColumn>
<ClientColumn>utilization</ClientColumn>
</SelectColumnList>
</NetworkObjectData>
<FlowFilterList>
<FlowFilter>
<FilterList>
<networkServiceId>160638846</networkServiceId>
<!--networkServiceId>150310084,148735991,150310811,160638846,160637025</networkServiceId-->
<!-- domainId>161319304</domainId-->
</FilterList>
</FlowFilter>
</FlowFilterList>
<FunctionList/>
<TimeDef>
<duration>YESTERDAY</duration>
<resolution>ONE_DAY</resolution>
</TimeDef>
<AggregateFlags>
<aggregateMe/>
<aggregateApp/>
</AggregateFlags>
<params>
<updateKeys/>
<includeVirtual/>
<skipAggregation>false</skipAggregation>
<skipBusinessLogic/>
</params>
</GenericClientQuery>
